pycbuf-0.1.2.dist-info/top_level.txt
pycbuf-0.1.2.dist-info/LICENSE.txt
pycbuf-0.1.2.dist-info/WHEEL
pycbuf-0.1.2.dist-info/METADATA
pycbuf-0.1.2.dist-info/RECORD
pycbuf/__init__.py
pycbuf/pycbuf.so
pycbuf-0.1.2.data/data/lib/libcbuf_parse_dynamic.so
pycbuf-0.1.2.data/data/lib/libuloglib.so
pycbuf-0.1.2.data/data/lib/libcbuf_stream.a
