Metadata-Version: 2.1
Name: pycbuf
Version: 0.1.2
Summary: Python implementation of CBUF message serialization
Home-page: https://github.com/Verdant-Robotics/cbuf
Author: Verdant Robotics
Author-email: info@verdantrobotics.com
License: Apache 2.0
Requires-Python: >=3.10
License-File: LICENSE.txt
